[
    {
        "title": "Admissions Open for Session 2025–26",
        "date": "2025-02-18",
        "isNew": true
    },
    {
        "title": "Diploma Examination Schedule Released",
        "date": "2025-02-15",
        "isNew": true
    },
    {
        "title": "Internship Drive for Final Year Students",
        "date": "2025-02-10",
        "isNew": false
    },
    {
        "title": "Scholarship Forms Now Available",
        "date": "2025-02-05",
        "isNew": false
    },
    {
        "title": "AI & Robotics Workshop on 10 March",
        "date": "2025-02-01",
        "isNew": false
    },
    {
        "title": "Campus Placement Orientation Program",
        "date": "2025-01-28",
        "isNew": false
    }
]
